firstcodewitharyan/__init__.py
firstcodewitharyan-0.3.dist-info/LICENSE.txt
firstcodewitharyan-0.3.dist-info/METADATA
firstcodewitharyan-0.3.dist-info/WHEEL
firstcodewitharyan-0.3.dist-info/top_level.txt
firstcodewitharyan-0.3.dist-info/RECORD
