Metadata-Version: 2.1
Name: firstcodewitharyan
Version: 0.3
Summary: Its About basic function and describing the function for sum and division
Author: Aryan Awasthi
Author-email: aranaw0035@gmail.com
Classifier: Programming Language :: Python :: 3
Classifier: License :: OSI Approved :: MIT License
Classifier: Operating System :: OS Independent
License-File: LICENSE.txt
